[
	{
		"Tom": "Hello"
	},
	{
		"Jenny": "You're Cute"
	},
	{
		"Tom": "Quite a nice day yeah"
	},
	{
		"Jenny": "Would you like to go somewhere?"
	},
	{
		"?": [
			{
                "1": [
                    "Lets go to he Beach!",
                    {
                        "Jenny": "Sure"
                    },
                    {
                        "EOD": "EOD"
                    }
                ]
			},
			{
				"2": [
					"Lets go home!",
					{
						"Tom": "lets go home!"
					},
					{
						"Jenny": "ok"
					},
					{
						"EOD": "EOD"
					}
				]
			}
		]
	}
]